dtw_sofar/__init__.py
dtw_sofar/__main__.py
dtw_sofar/dtw_sofar.py
dtw_sofar/tests/expected_dtw_matrix.pickle
dtw_sofar/tests/expected_final_path.pickle
dtw_sofar/tests/expected_otf_path.pickle
dtw_sofar/tests/expected_preds.pickle
dtw_sofar/tests/test_all.py
dtw_sofar-0.1.2.dist-info/LICENSE
dtw_sofar-0.1.2.dist-info/METADATA
dtw_sofar-0.1.2.dist-info/WHEEL
dtw_sofar-0.1.2.dist-info/top_level.txt
dtw_sofar-0.1.2.dist-info/RECORD
